aleksis/apps/dashboardfeeds/__init__.py
aleksis/apps/dashboardfeeds/admin.py
aleksis/apps/dashboardfeeds/apps.py
aleksis/apps/dashboardfeeds/locale/.keepdir
aleksis/apps/dashboardfeeds/locale/ar/LC_MESSAGES/django.mo
aleksis/apps/dashboardfeeds/locale/ar/LC_MESSAGES/django.po
aleksis/apps/dashboardfeeds/locale/de_DE/LC_MESSAGES/django.mo
aleksis/apps/dashboardfeeds/locale/de_DE/LC_MESSAGES/django.po
aleksis/apps/dashboardfeeds/locale/fr/LC_MESSAGES/django.mo
aleksis/apps/dashboardfeeds/locale/fr/LC_MESSAGES/django.po
aleksis/apps/dashboardfeeds/locale/la/LC_MESSAGES/django.mo
aleksis/apps/dashboardfeeds/locale/la/LC_MESSAGES/django.po
aleksis/apps/dashboardfeeds/locale/nb_NO/LC_MESSAGES/django.mo
aleksis/apps/dashboardfeeds/locale/nb_NO/LC_MESSAGES/django.po
aleksis/apps/dashboardfeeds/locale/ru/LC_MESSAGES/django.mo
aleksis/apps/dashboardfeeds/locale/ru/LC_MESSAGES/django.po
aleksis/apps/dashboardfeeds/locale/tr_TR/LC_MESSAGES/django.mo
aleksis/apps/dashboardfeeds/locale/tr_TR/LC_MESSAGES/django.po
aleksis/apps/dashboardfeeds/locale/uk/LC_MESSAGES/django.mo
aleksis/apps/dashboardfeeds/locale/uk/LC_MESSAGES/django.po
aleksis/apps/dashboardfeeds/migrations/0001_initial.py
aleksis/apps/dashboardfeeds/migrations/0002_link_field_optional.py
aleksis/apps/dashboardfeeds/migrations/__init__.py
aleksis/apps/dashboardfeeds/models.py
aleksis/apps/dashboardfeeds/settings.py
aleksis/apps/dashboardfeeds/static/.keepdir
aleksis/apps/dashboardfeeds/static/dashboardfeeds/css/style.css
aleksis/apps/dashboardfeeds/static/dashboardfeeds/image_not_found.png
aleksis/apps/dashboardfeeds/tasks.py
aleksis/apps/dashboardfeeds/templates/dashboardfeeds/ical.html
aleksis/apps/dashboardfeeds/templates/dashboardfeeds/rss.html
aleksis/apps/dashboardfeeds/util/__init__.py
aleksis/apps/dashboardfeeds/util/event_feed.py
aleksis_app_dashboardfeeds-4.0.0.dist-info/LICENCE.rst
aleksis_app_dashboardfeeds-4.0.0.dist-info/METADATA
aleksis_app_dashboardfeeds-4.0.0.dist-info/WHEEL
aleksis_app_dashboardfeeds-4.0.0.dist-info/entry_points.txt
aleksis_app_dashboardfeeds-4.0.0.dist-info/RECORD
