Metadata-Version: 2.3
Name: AlekSIS-App-DashboardFeeds
Version: 4.0.0
Summary: AlekSIS (School Information System) — App Dashboard Feeds (Include feeds from external resources as widgets on dashboard)
License: EUPL-1.2-or-later
Keywords: SIS,education,school,calendar,rss
Author: Julian Leucker
Author-email: leuckerj@gmail.com
Maintainer: Jonathan Weth
Maintainer-email: jonathan.weth@teckids.org
Requires-Python: >=3.10,<4.0
Classifier: Development Status :: 5 - Production/Stable
Classifier: Environment :: Web Environment
Classifier: Framework :: Django :: 3.0
Classifier: Intended Audience :: Education
Classifier: License :: Other/Proprietary License
Classifier: Programming Language :: Python :: 3
Classifier: Programming Language :: Python :: 3.10
Classifier: Programming Language :: Python :: 3.11
Classifier: Programming Language :: Python :: 3.12
Classifier: Programming Language :: Python :: 3.13
Classifier: Topic :: Education
Classifier: Typing :: Typed
Requires-Dist: aleksis-core (>=4.0.0,<5.0.0)
Requires-Dist: django-feed-reader (>=2.0.0,<3.0.0)
Requires-Dist: feedparser (>=6.0.0,<7.0.0)
Requires-Dist: ics (>=0.7,<0.8)
Project-URL: Documentation, https://aleksis.org/AlekSIS/docs/html/
Project-URL: Homepage, https://aleksis.org
Project-URL: Repository, https://edugit.org/AlekSIS/official/AlekSIS-App-DashboardFeeds
